{
    "created_at": "Sat Feb 08 04:49:59 +0000 2020",
    "id": 1226005231307304960,
    "id_str": "1226005231307304960",
    "text": "@XraypadOfficial Do yall have any coupons i could use 🤫",
    "truncated": false,
    "entities": {
        "hashtags": [],
        "symbols": [],
        "user_mentions": [
            {
                "screen_name": "XraypadOfficial",
                "name": "X-raypadOffical",
                "id": 888684012,
                "id_str": "888684012",
                "indices": [
                    0,
                    16
                ]
            }
        ],
        "urls": []
    },
    "source": "<a href=\"http://twitter.com/download/android\" rel=\"nofollow\">Twitter for Android</a>",
    "in_reply_to_status_id": 1225301146614431744,
    "in_reply_to_status_id_str": "1225301146614431744",
    "in_reply_to_user_id": 888684012,
    "in_reply_to_user_id_str": "888684012",
    "in_reply_to_screen_name": "XraypadOfficial",
    "user": {
        "id": 1126412870042841093,
        "id_str": "1126412870042841093",
        "name": "uG Exo",
        "screen_name": "exocs_",
        "location": "Ocean waves",
        "description": "19 | Amateur Valorant for @UniongamingESP top 4k SEA | 125k grid 🎯",
        "url": "https://t.co/s7rXSYaHv6",
        "entities": {
            "url": {
                "urls": [
                    {
                        "url": "https://t.co/s7rXSYaHv6",
                        "expanded_url": "https://youtu.be/UICfTd9SECc",
                        "display_url": "youtu.be/UICfTd9SECc",
                        "indices": [
                            0,
                            23
                        ]
                    }
                ]
            },
            "description": {
                "urls": []
            }
        },
        "protected": false,
        "followers_count": 102,
        "friends_count": 808,
        "listed_count": 0,
        "created_at": "Thu May 09 09:05:30 +0000 2019",
        "favourites_count": 7026,
        "utc_offset": null,
        "time_zone": null,
        "geo_enabled": false,
        "verified": false,
        "statuses_count": 2245,
        "lang": null,
        "contributors_enabled": false,
        "is_translator": false,
        "is_translation_enabled": false,
        "profile_background_color": "F5F8FA",
        "profile_background_image_url": null,
        "profile_background_image_url_https": null,
        "profile_background_tile": false,
        "profile_image_url": "http://pbs.twimg.com/profile_images/1487385813780508672/xaKzjOE-_normal.jpg",
        "profile_image_url_https": "https://pbs.twimg.com/profile_images/1487385813780508672/xaKzjOE-_normal.jpg",
        "profile_banner_url": "https://pbs.twimg.com/profile_banners/1126412870042841093/1650524018",
        "profile_link_color": "1DA1F2",
        "profile_sidebar_border_color": "C0DEED",
        "profile_sidebar_fill_color": "DDEEF6",
        "profile_text_color": "333333",
        "profile_use_background_image": true,
        "has_extended_profile": false,
        "default_profile": true,
        "default_profile_image": false,
        "following": false,
        "follow_request_sent": false,
        "notifications": false,
        "translator_type": "none",
        "withheld_in_countries": []
    },
    "geo": null,
    "coordinates": null,
    "place": null,
    "contributors": null,
    "is_quote_status": false,
    "retweet_count": 0,
    "favorite_count": 0,
    "favorited": false,
    "retweeted": false,
    "lang": "en"
}