{
    "created_at": "Sun Apr 26 07:12:37 +0000 2020",
    "id": 1254307378033557504,
    "id_str": "1254307378033557504",
    "text": "@Dant_ey @CACCOT1 They shouldn't Lockdown then sebi it's food they want to eat.",
    "truncated": false,
    "entities": {
        "hashtags": [],
        "symbols": [],
        "user_mentions": [
            {
                "screen_name": "Dant_ey",
                "name": "⛑ D'HD",
                "id": 1088546002196414464,
                "id_str": "1088546002196414464",
                "indices": [
                    0,
                    8
                ]
            },
            {
                "screen_name": "CACCOT1",
                "name": "Opeyemi Babalola",
                "id": 813016272439013376,
                "id_str": "813016272439013376",
                "indices": [
                    9,
                    17
                ]
            }
        ],
        "urls": []
    },
    "source": "<a href=\"https://mobile.twitter.com\" rel=\"nofollow\">Twitter Web App</a>",
    "in_reply_to_status_id": 1254303759896907776,
    "in_reply_to_status_id_str": "1254303759896907776",
    "in_reply_to_user_id": 1088546002196414464,
    "in_reply_to_user_id_str": "1088546002196414464",
    "in_reply_to_screen_name": "Dant_ey",
    "user": {
        "id": 311177486,
        "id_str": "311177486",
        "name": "Temidayo🇲🇹🇪🇸",
        "screen_name": "Stephen_dayo",
        "location": "",
        "description": "Travel Consultant || Study Advisor @gladgateltd || Brand Strategist @smartrobtech",
        "url": null,
        "entities": {
            "description": {
                "urls": []
            }
        },
        "protected": false,
        "followers_count": 1859,
        "friends_count": 4998,
        "listed_count": 9,
        "created_at": "Sun Jun 05 01:11:09 +0000 2011",
        "favourites_count": 16867,
        "utc_offset": null,
        "time_zone": null,
        "geo_enabled": true,
        "verified": false,
        "statuses_count": 22578,
        "lang": null,
        "contributors_enabled": false,
        "is_translator": false,
        "is_translation_enabled": false,
        "profile_background_color": "000000",
        "profile_background_image_url": "http://abs.twimg.com/images/themes/theme1/bg.png",
        "profile_background_image_url_https": "https://abs.twimg.com/images/themes/theme1/bg.png",
        "profile_background_tile": false,
        "profile_image_url": "http://pbs.twimg.com/profile_images/1502040686798987270/TIvo0MsF_normal.jpg",
        "profile_image_url_https": "https://pbs.twimg.com/profile_images/1502040686798987270/TIvo0MsF_normal.jpg",
        "profile_link_color": "981CEB",
        "profile_sidebar_border_color": "000000",
        "profile_sidebar_fill_color": "000000",
        "profile_text_color": "000000",
        "profile_use_background_image": false,
        "has_extended_profile": true,
        "default_profile": false,
        "default_profile_image": false,
        "following": false,
        "follow_request_sent": false,
        "notifications": false,
        "translator_type": "none",
        "withheld_in_countries": []
    },
    "geo": null,
    "coordinates": null,
    "place": null,
    "contributors": null,
    "is_quote_status": false,
    "retweet_count": 0,
    "favorite_count": 1,
    "favorited": false,
    "retweeted": false,
    "lang": "en"
}