{
    "contributors": null,
    "coordinates": null,
    "created_at": "Wed Jul 01 11:57:35 +0000 2020",
    "entities": {
        "hashtags": [],
        "symbols": [],
        "urls": [
            {
                "display_url": "twitter.com/i/web/status/1\u2026",
                "expanded_url": "https://twitter.com/i/web/status/1278296689661612033",
                "indices": [
                    117,
                    140
                ],
                "url": "https://t.co/ZdfjwDmR13"
            }
        ],
        "user_mentions": [
            {
                "id": 87679233,
                "id_str": "87679233",
                "indices": [
                    0,
                    13
                ],
                "name": "Alex Berenson",
                "screen_name": "AlexBerenson"
            },
            {
                "id": 18080108,
                "id_str": "18080108",
                "indices": [
                    14,
                    21
                ],
                "name": "Tom Nelson",
                "screen_name": "tan123"
            }
        ]
    },
    "favorite_count": 0,
    "favorited": false,
    "geo": null,
    "id": 1278296689661612033,
    "id_str": "1278296689661612033",
    "in_reply_to_screen_name": "AlexBerenson",
    "in_reply_to_status_id": 1278168876027650049,
    "in_reply_to_status_id_str": "1278168876027650049",
    "in_reply_to_user_id": 87679233,
    "in_reply_to_user_id_str": "87679233",
    "is_quote_status": false,
    "lang": "en",
    "place": null,
    "retweet_count": 0,
    "retweeted": false,
    "source": "<a href=\"https://mobile.twitter.com\" rel=\"nofollow\">Twitter Web App</a>",
    "text": "@AlexBerenson @tan123 Of course, they can manage to produce tests that over report positives by 50% but not antibod\u2026 https://t.co/ZdfjwDmR13",
    "truncated": true,
    "user": {
        "contributors_enabled": false,
        "created_at": "Mon Mar 09 18:47:12 +0000 2020",
        "default_profile": true,
        "default_profile_image": false,
        "description": "Nope",
        "entities": {
            "description": {
                "urls": []
            },
            "url": {
                "urls": [
                    {
                        "display_url": "whocares.com",
                        "expanded_url": "http://www.whocares.com",
                        "indices": [
                            0,
                            23
                        ],
                        "url": "https://t.co/dDsks68nG1"
                    }
                ]
            }
        },
        "favourites_count": 2536,
        "follow_request_sent": false,
        "followers_count": 16,
        "following": false,
        "friends_count": 141,
        "geo_enabled": false,
        "has_extended_profile": false,
        "id": 1237087501619212288,
        "id_str": "1237087501619212288",
        "is_translation_enabled": false,
        "is_translator": false,
        "lang": null,
        "listed_count": 1,
        "location": "Why?",
        "name": "James Stevens",
        "notifications": false,
        "profile_background_color": "F5F8FA",
        "profile_background_image_url": null,
        "profile_background_image_url_https": null,
        "profile_background_tile": false,
        "profile_image_url": "http://pbs.twimg.com/profile_images/1248292391548682240/evqWvC7v_normal.jpg",
        "profile_image_url_https": "https://pbs.twimg.com/profile_images/1248292391548682240/evqWvC7v_normal.jpg",
        "profile_link_color": "1DA1F2",
        "profile_sidebar_border_color": "C0DEED",
        "profile_sidebar_fill_color": "DDEEF6",
        "profile_text_color": "333333",
        "profile_use_background_image": true,
        "protected": false,
        "screen_name": "JamesSt08393704",
        "statuses_count": 4842,
        "time_zone": null,
        "translator_type": "none",
        "url": "https://t.co/dDsks68nG1",
        "utc_offset": null,
        "verified": false,
        "withheld_in_countries": []
    }
}