{
    "contributors": null,
    "coordinates": null,
    "created_at": "Thu Jul 17 20:52:21 +0000 2014",
    "entities": {
        "hashtags": [
            {
                "indices": [
                    90,
                    95
                ],
                "text": "MH17"
            }
        ],
        "media": [
            {
                "display_url": "pic.twitter.com/jUd4X3Rym3",
                "expanded_url": "https://twitter.com/nycjim/status/489872500462190593/photo/1",
                "id": 489872499476152320,
                "id_str": "489872499476152320",
                "indices": [
                    121,
                    143
                ],
                "media_url": "http://pbs.twimg.com/media/BsxgcVyCQAATOUs.jpg",
                "media_url_https": "https://pbs.twimg.com/media/BsxgcVyCQAATOUs.jpg",
                "sizes": {
                    "large": {
                        "h": 368,
                        "resize": "fit",
                        "w": 638
                    },
                    "medium": {
                        "h": 368,
                        "resize": "fit",
                        "w": 638
                    },
                    "small": {
                        "h": 368,
                        "resize": "fit",
                        "w": 638
                    },
                    "thumb": {
                        "h": 150,
                        "resize": "crop",
                        "w": 150
                    }
                },
                "source_status_id": 489872500462190593,
                "source_status_id_str": "489872500462190593",
                "source_user_id": 14940354,
                "source_user_id_str": "14940354",
                "type": "photo",
                "url": "http://t.co/jUd4X3Rym3"
            }
        ],
        "symbols": [],
        "urls": [
            {
                "display_url": "on.mash.to/1pfECSd",
                "expanded_url": "http://on.mash.to/1pfECSd",
                "indices": [
                    97,
                    119
                ],
                "url": "http://t.co/NSVlPhf5uN"
            }
        ],
        "user_mentions": []
    },
    "extended_entities": {
        "media": [
            {
                "display_url": "pic.twitter.com/jUd4X3Rym3",
                "expanded_url": "https://twitter.com/nycjim/status/489872500462190593/photo/1",
                "id": 489872499476152320,
                "id_str": "489872499476152320",
                "indices": [
                    121,
                    143
                ],
                "media_url": "http://pbs.twimg.com/media/BsxgcVyCQAATOUs.jpg",
                "media_url_https": "https://pbs.twimg.com/media/BsxgcVyCQAATOUs.jpg",
                "sizes": {
                    "large": {
                        "h": 368,
                        "resize": "fit",
                        "w": 638
                    },
                    "medium": {
                        "h": 368,
                        "resize": "fit",
                        "w": 638
                    },
                    "small": {
                        "h": 368,
                        "resize": "fit",
                        "w": 638
                    },
                    "thumb": {
                        "h": 150,
                        "resize": "crop",
                        "w": 150
                    }
                },
                "source_status_id": 489872500462190593,
                "source_status_id_str": "489872500462190593",
                "source_user_id": 14940354,
                "source_user_id_str": "14940354",
                "type": "photo",
                "url": "http://t.co/jUd4X3Rym3"
            }
        ]
    },
    "favorite_count": 0,
    "favorited": false,
    "geo": null,
    "id": 489875274960367617,
    "id_str": "489875274960367617",
    "in_reply_to_screen_name": "nycjim",
    "in_reply_to_status_id": 489872500462190593,
    "in_reply_to_status_id_str": "489872500462190593",
    "in_reply_to_user_id": 14940354,
    "in_reply_to_user_id_str": "14940354",
    "is_quote_status": false,
    "lang": "en",
    "place": null,
    "possibly_sensitive": false,
    "retweet_count": 0,
    "retweeted": false,
    "source": "<a href=\"http://twitter.com\" rel=\"nofollow\">Twitter Web Client</a>",
    "text": "1/2RT@nycjim Leaked phone call/rebel leader &amp;Russian intel agent:\u201cCossacks\u201d shot down #MH17. http://t.co/NSVlPhf5uN  http://t.co/jUd4X3Rym3",
    "truncated": false,
    "user": {
        "contributors_enabled": false,
        "created_at": "Thu Aug 27 10:49:23 +0000 2009",
        "default_profile": false,
        "default_profile_image": false,
        "description": "Attorney & Child Welfare Advocate. Adjunct Prof (legal ethics) @FordhamLawNYC & @TempleLaw (Tokyo). @FCAANational @miltonhershey alum (7 YRS)",
        "entities": {
            "description": {
                "urls": []
            },
            "url": {
                "urls": [
                    {
                        "display_url": "protecthersheychildren.org",
                        "expanded_url": "http://protecthersheychildren.org",
                        "indices": [
                            0,
                            23
                        ],
                        "url": "https://t.co/X1GjtK8ZnY"
                    }
                ]
            }
        },
        "favourites_count": 78644,
        "follow_request_sent": false,
        "followers_count": 1609,
        "following": false,
        "friends_count": 441,
        "geo_enabled": false,
        "has_extended_profile": false,
        "id": 69259701,
        "id_str": "69259701",
        "is_translation_enabled": false,
        "is_translator": false,
        "lang": null,
        "listed_count": 74,
        "location": "New York, NY & Tokyo, Japan",
        "name": "Ric Fouad",
        "notifications": false,
        "profile_background_color": "C0DEED",
        "profile_background_image_url": "http://abs.twimg.com/images/themes/theme1/bg.png",
        "profile_background_image_url_https": "https://abs.twimg.com/images/themes/theme1/bg.png",
        "profile_background_tile": false,
        "profile_banner_url": "https://pbs.twimg.com/profile_banners/69259701/1623604136",
        "profile_image_url": "http://pbs.twimg.com/profile_images/1347553654157488132/nWIk1q-t_normal.jpg",
        "profile_image_url_https": "https://pbs.twimg.com/profile_images/1347553654157488132/nWIk1q-t_normal.jpg",
        "profile_link_color": "0084B4",
        "profile_sidebar_border_color": "FFFFFF",
        "profile_sidebar_fill_color": "DDEEF6",
        "profile_text_color": "333333",
        "profile_use_background_image": false,
        "protected": false,
        "screen_name": "ricfouad",
        "statuses_count": 58619,
        "time_zone": null,
        "translator_type": "none",
        "url": "https://t.co/X1GjtK8ZnY",
        "utc_offset": null,
        "verified": false,
        "withheld_in_countries": []
    }
}