{
    "created_at": "Tue Aug 05 21:23:56 +0000 2014",
    "id": 496768590914531330,
    "id_str": "496768590914531330",
    "text": "“@JBCrewdotcom: \"Justin Bieber ringtone saves Russian fisherman from potentially fatal bear attack.\"”boss",
    "truncated": false,
    "entities": {
        "hashtags": [],
        "symbols": [],
        "user_mentions": [
            {
                "screen_name": "JBCrewdotcom",
                "name": "Justin Bieber Crew",
                "id": 1439055242,
                "id_str": "1439055242",
                "indices": [
                    1,
                    14
                ]
            }
        ],
        "urls": []
    },
    "source": "<a href=\"http://twitter.com/download/iphone\" rel=\"nofollow\">Twitter for iPhone</a>",
    "in_reply_to_status_id": 496698590153416704,
    "in_reply_to_status_id_str": "496698590153416704",
    "in_reply_to_user_id": 1239313056,
    "in_reply_to_user_id_str": "1239313056",
    "in_reply_to_screen_name": "JBCrewposts",
    "user": {
        "id": 231868366,
        "id_str": "231868366",
        "name": "K ♡♡",
        "screen_name": "shellyluvsu",
        "location": "тнe new cιтy oғ yorĸ",
        "description": "Be kind today, remind everyone tomorrow. #Belieber ♡♡",
        "url": "https://t.co/IWlnqSPW1m",
        "entities": {
            "url": {
                "urls": [
                    {
                        "url": "https://t.co/IWlnqSPW1m",
                        "expanded_url": "https://www.snapchat.com/add/kechidagoat",
                        "display_url": "snapchat.com/add/kechidagoat",
                        "indices": [
                            0,
                            23
                        ]
                    }
                ]
            },
            "description": {
                "urls": []
            }
        },
        "protected": false,
        "followers_count": 15904,
        "friends_count": 3195,
        "listed_count": 51,
        "created_at": "Wed Dec 29 17:49:12 +0000 2010",
        "favourites_count": 17359,
        "utc_offset": null,
        "time_zone": null,
        "geo_enabled": false,
        "verified": false,
        "statuses_count": 72716,
        "lang": null,
        "contributors_enabled": false,
        "is_translator": false,
        "is_translation_enabled": false,
        "profile_background_color": "AA10DE",
        "profile_background_image_url": "http://abs.twimg.com/images/themes/theme1/bg.png",
        "profile_background_image_url_https": "https://abs.twimg.com/images/themes/theme1/bg.png",
        "profile_background_tile": true,
        "profile_image_url": "http://pbs.twimg.com/profile_images/1398958320296288257/yZjp4-lp_normal.jpg",
        "profile_image_url_https": "https://pbs.twimg.com/profile_images/1398958320296288257/yZjp4-lp_normal.jpg",
        "profile_banner_url": "https://pbs.twimg.com/profile_banners/231868366/1622372811",
        "profile_link_color": "FA0ABA",
        "profile_sidebar_border_color": "FFFFFF",
        "profile_sidebar_fill_color": "DDEEF6",
        "profile_text_color": "2F0778",
        "profile_use_background_image": true,
        "has_extended_profile": true,
        "default_profile": false,
        "default_profile_image": false,
        "following": false,
        "follow_request_sent": false,
        "notifications": false,
        "translator_type": "none",
        "withheld_in_countries": []
    },
    "geo": null,
    "coordinates": null,
    "place": null,
    "contributors": null,
    "is_quote_status": false,
    "retweet_count": 0,
    "favorite_count": 0,
    "favorited": false,
    "retweeted": false,
    "lang": "en"
}