{
    "contributors": null,
    "coordinates": null,
    "created_at": "Tue Sep 09 22:21:06 +0000 2014",
    "entities": {
        "hashtags": [],
        "symbols": [],
        "urls": [],
        "user_mentions": [
            {
                "id": 14372486,
                "id_str": "14372486",
                "indices": [
                    0,
                    9
                ],
                "name": "Engadget",
                "screen_name": "engadget"
            },
            {
                "id": 13317162,
                "id_str": "13317162",
                "indices": [
                    10,
                    15
                ],
                "name": "Self-Aware \ud83d\udd3a\ud83d\udd28\u26a1\ufe0f\ud83d\udcaa \ud83c\udf0e (\u2744\ufe0f,\u2744\ufe0f)",
                "screen_name": "F1sT"
            }
        ]
    },
    "favorite_count": 0,
    "favorited": false,
    "geo": null,
    "id": 509466552501288960,
    "id_str": "509466552501288960",
    "in_reply_to_screen_name": "engadget",
    "in_reply_to_status_id": 509466295344304129,
    "in_reply_to_status_id_str": "509466295344304129",
    "in_reply_to_user_id": 14372486,
    "in_reply_to_user_id_str": "14372486",
    "is_quote_status": false,
    "lang": "en",
    "place": null,
    "retweet_count": 1,
    "retweeted": false,
    "source": "<a href=\"http://itunes.apple.com/us/app/twitter/id409789998?mt=12\" rel=\"nofollow\">Twitter for Mac</a>",
    "text": "@engadget @f1st looks like no mine craft on ps4",
    "truncated": false,
    "user": {
        "contributors_enabled": false,
        "created_at": "Wed Mar 03 01:24:50 +0000 2010",
        "default_profile": true,
        "default_profile_image": false,
        "description": "",
        "entities": {
            "description": {
                "urls": []
            }
        },
        "favourites_count": 460,
        "follow_request_sent": false,
        "followers_count": 31,
        "following": false,
        "friends_count": 273,
        "geo_enabled": true,
        "has_extended_profile": true,
        "id": 119228054,
        "id_str": "119228054",
        "is_translation_enabled": false,
        "is_translator": false,
        "lang": null,
        "listed_count": 1,
        "location": "",
        "name": "Joepeps",
        "notifications": false,
        "profile_background_color": "C0DEED",
        "profile_background_image_url": "http://abs.twimg.com/images/themes/theme1/bg.png",
        "profile_background_image_url_https": "https://abs.twimg.com/images/themes/theme1/bg.png",
        "profile_background_tile": false,
        "profile_image_url": "http://pbs.twimg.com/profile_images/891664494006554625/kd9aVYUV_normal.jpg",
        "profile_image_url_https": "https://pbs.twimg.com/profile_images/891664494006554625/kd9aVYUV_normal.jpg",
        "profile_link_color": "1DA1F2",
        "profile_sidebar_border_color": "C0DEED",
        "profile_sidebar_fill_color": "DDEEF6",
        "profile_text_color": "333333",
        "profile_use_background_image": true,
        "protected": false,
        "screen_name": "joepeps11",
        "statuses_count": 2675,
        "time_zone": null,
        "translator_type": "none",
        "url": null,
        "utc_offset": null,
        "verified": false,
        "withheld_in_countries": []
    }
}