{
    "contributors": null,
    "coordinates": null,
    "created_at": "Mon Sep 29 19:56:59 +0000 2014",
    "entities": {
        "hashtags": [],
        "symbols": [],
        "urls": [],
        "user_mentions": [
            {
                "id": 893966122109853696,
                "id_str": "893966122109853696",
                "indices": [
                    0,
                    16
                ],
                "name": "Placeholder",
                "screen_name": "DavidJo52951945"
            }
        ]
    },
    "favorite_count": 2,
    "favorited": false,
    "geo": null,
    "id": 516678043730210819,
    "id_str": "516678043730210819",
    "in_reply_to_screen_name": "DavidJoBrexit",
    "in_reply_to_status_id": 516636338679197697,
    "in_reply_to_status_id_str": "516636338679197697",
    "in_reply_to_user_id": 1125937411,
    "in_reply_to_user_id_str": "1125937411",
    "is_quote_status": false,
    "lang": "en",
    "place": null,
    "retweet_count": 0,
    "retweeted": false,
    "source": "<a href=\"https://twitter.com/download/android\" rel=\"nofollow\">Twitter for Android Tablets</a>",
    "text": "@DavidJo52951945  negative. Then we lose ground. We fight and take back whats ours. Either they abide by our rules or they can leave.",
    "truncated": false,
    "user": {
        "contributors_enabled": false,
        "created_at": "Thu Mar 13 17:24:39 +0000 2014",
        "default_profile": true,
        "default_profile_image": false,
        "description": "Military- active/ret desired priority, PRO constitution/PRO life/Americas Vets/ PRO military/militia/God & Country. #2a #MAGA",
        "entities": {
            "description": {
                "urls": []
            }
        },
        "favourites_count": 11494,
        "follow_request_sent": false,
        "followers_count": 534,
        "following": false,
        "friends_count": 647,
        "geo_enabled": true,
        "has_extended_profile": false,
        "id": 2387505620,
        "id_str": "2387505620",
        "is_translation_enabled": false,
        "is_translator": false,
        "lang": null,
        "listed_count": 10,
        "location": "Murphy,Nc",
        "name": "Big Country",
        "notifications": false,
        "profile_background_color": "C0DEED",
        "profile_background_image_url": "http://abs.twimg.com/images/themes/theme1/bg.png",
        "profile_background_image_url_https": "https://abs.twimg.com/images/themes/theme1/bg.png",
        "profile_background_tile": false,
        "profile_banner_url": "https://pbs.twimg.com/profile_banners/2387505620/1610479694",
        "profile_image_url": "http://pbs.twimg.com/profile_images/1062769607755345923/W5zoO-Bt_normal.jpg",
        "profile_image_url_https": "https://pbs.twimg.com/profile_images/1062769607755345923/W5zoO-Bt_normal.jpg",
        "profile_link_color": "1DA1F2",
        "profile_sidebar_border_color": "C0DEED",
        "profile_sidebar_fill_color": "DDEEF6",
        "profile_text_color": "333333",
        "profile_use_background_image": true,
        "protected": false,
        "screen_name": "isaiahdmason",
        "statuses_count": 14930,
        "time_zone": null,
        "translator_type": "none",
        "url": null,
        "utc_offset": null,
        "verified": false,
        "withheld_in_countries": []
    }
}