{
    "contributors": null,
    "coordinates": null,
    "created_at": "Mon Oct 20 13:58:14 +0000 2014",
    "entities": {
        "hashtags": [],
        "media": [
            {
                "display_url": "pic.twitter.com/lyQRb4ODBf",
                "expanded_url": "https://twitter.com/fxnscitech/status/524185876931162112/photo/1",
                "id": 524185876033990656,
                "id_str": "524185876033990656",
                "indices": [
                    115,
                    137
                ],
                "media_url": "http://pbs.twimg.com/media/B0ZIRulIcAAWmPw.jpg",
                "media_url_https": "https://pbs.twimg.com/media/B0ZIRulIcAAWmPw.jpg",
                "sizes": {
                    "large": {
                        "h": 493,
                        "resize": "fit",
                        "w": 876
                    },
                    "medium": {
                        "h": 493,
                        "resize": "fit",
                        "w": 876
                    },
                    "small": {
                        "h": 383,
                        "resize": "fit",
                        "w": 680
                    },
                    "thumb": {
                        "h": 150,
                        "resize": "crop",
                        "w": 150
                    }
                },
                "source_status_id": 524185876931162112,
                "source_status_id_str": "524185876931162112",
                "source_user_id": 107114063,
                "source_user_id_str": "107114063",
                "type": "photo",
                "url": "http://t.co/lyQRb4ODBf"
            }
        ],
        "symbols": [],
        "urls": [
            {
                "display_url": "fxn.ws/1t2ePlj",
                "expanded_url": "http://fxn.ws/1t2ePlj",
                "indices": [
                    92,
                    114
                ],
                "url": "http://t.co/CxUOw7dS7S"
            }
        ],
        "user_mentions": [
            {
                "id": 840878926700400640,
                "id_str": "840878926700400640",
                "indices": [
                    11,
                    22
                ],
                "name": "Sheron Zuccarelli",
                "screen_name": "fxnscitech"
            },
            {
                "id": 15428397,
                "id_str": "15428397",
                "indices": [
                    77,
                    89
                ],
                "name": "Live Science",
                "screen_name": "LiveScience"
            }
        ]
    },
    "extended_entities": {
        "media": [
            {
                "display_url": "pic.twitter.com/lyQRb4ODBf",
                "expanded_url": "https://twitter.com/fxnscitech/status/524185876931162112/photo/1",
                "id": 524185876033990656,
                "id_str": "524185876033990656",
                "indices": [
                    115,
                    137
                ],
                "media_url": "http://pbs.twimg.com/media/B0ZIRulIcAAWmPw.jpg",
                "media_url_https": "https://pbs.twimg.com/media/B0ZIRulIcAAWmPw.jpg",
                "sizes": {
                    "large": {
                        "h": 493,
                        "resize": "fit",
                        "w": 876
                    },
                    "medium": {
                        "h": 493,
                        "resize": "fit",
                        "w": 876
                    },
                    "small": {
                        "h": 383,
                        "resize": "fit",
                        "w": 680
                    },
                    "thumb": {
                        "h": 150,
                        "resize": "crop",
                        "w": 150
                    }
                },
                "source_status_id": 524185876931162112,
                "source_status_id_str": "524185876931162112",
                "source_user_id": 107114063,
                "source_user_id_str": "107114063",
                "type": "photo",
                "url": "http://t.co/lyQRb4ODBf"
            }
        ]
    },
    "favorite_count": 0,
    "favorited": false,
    "geo": null,
    "id": 524197906409328640,
    "id_str": "524197906409328640",
    "in_reply_to_screen_name": "FoxNewsTech",
    "in_reply_to_status_id": 524185876931162112,
    "in_reply_to_status_id_str": "524185876931162112",
    "in_reply_to_user_id": 107114063,
    "in_reply_to_user_id_str": "107114063",
    "is_quote_status": false,
    "lang": "en",
    "place": null,
    "possibly_sensitive": false,
    "retweet_count": 0,
    "retweeted": false,
    "source": "<a href=\"http://twitter.com/download/iphone\" rel=\"nofollow\">Twitter for iPhone</a>",
    "text": "NOOOOOOPE \u201c@fxnscitech: Puppy-sized spider surprises scientist in rainforest @LiveScience | http://t.co/CxUOw7dS7S http://t.co/lyQRb4ODBf\u201d",
    "truncated": false,
    "user": {
        "contributors_enabled": false,
        "created_at": "Mon Dec 08 22:50:10 +0000 2008",
        "default_profile": false,
        "default_profile_image": false,
        "description": "I'm a root beer drinking Libertarian who watches movies. The Asylum is my jam. I own way too many board games. Non-expert at Screen Rant.",
        "entities": {
            "description": {
                "urls": []
            },
            "url": {
                "urls": [
                    {
                        "display_url": "screenrant.com",
                        "expanded_url": "http://screenrant.com",
                        "indices": [
                            0,
                            23
                        ],
                        "url": "https://t.co/6KWOEewTyB"
                    }
                ]
            }
        },
        "favourites_count": 32392,
        "follow_request_sent": false,
        "followers_count": 2632,
        "following": false,
        "friends_count": 1549,
        "geo_enabled": false,
        "has_extended_profile": false,
        "id": 17976213,
        "id_str": "17976213",
        "is_translation_enabled": false,
        "is_translator": false,
        "lang": null,
        "listed_count": 87,
        "location": "Florida",
        "name": "Jags Board Game & Movie Guy",
        "notifications": false,
        "profile_background_color": "022330",
        "profile_background_image_url": "http://abs.twimg.com/images/themes/theme1/bg.png",
        "profile_background_image_url_https": "https://abs.twimg.com/images/themes/theme1/bg.png",
        "profile_background_tile": false,
        "profile_banner_url": "https://pbs.twimg.com/profile_banners/17976213/1548167101",
        "profile_image_url": "http://pbs.twimg.com/profile_images/1391117266197094400/Wd4MoLg9_normal.jpg",
        "profile_image_url_https": "https://pbs.twimg.com/profile_images/1391117266197094400/Wd4MoLg9_normal.jpg",
        "profile_link_color": "0084B4",
        "profile_sidebar_border_color": "A8C7F7",
        "profile_sidebar_fill_color": "C0DFEC",
        "profile_text_color": "333333",
        "profile_use_background_image": false,
        "protected": false,
        "screen_name": "MoviePaul",
        "statuses_count": 103612,
        "time_zone": null,
        "translator_type": "none",
        "url": "https://t.co/6KWOEewTyB",
        "utc_offset": null,
        "verified": false,
        "withheld_in_countries": []
    }
}