{
    "created_at": "Sat Nov 08 16:22:49 +0000 2014",
    "id": 531119662151786496,
    "id_str": "531119662151786496",
    "text": "“@BuzzFeed:Pepsi Is ActuallyTesting A Doritos-Flavored Mountain Dew\nhttp://t.co/KB5UANpDSr http://t.co/N826YRUFMY” @Brungus_ @RealBabyStevie",
    "truncated": false,
    "entities": {
        "hashtags": [],
        "symbols": [],
        "user_mentions": [
            {
                "screen_name": "BuzzFeed",
                "name": "BuzzFeed",
                "id": 5695632,
                "id_str": "5695632",
                "indices": [
                    1,
                    10
                ]
            },
            {
                "screen_name": "brungus_",
                "name": "brungus_",
                "id": 754339994664181760,
                "id_str": "754339994664181760",
                "indices": [
                    115,
                    124
                ]
            },
            {
                "screen_name": "RealBabyStevie",
                "name": "chicken steve",
                "id": 1896271122,
                "id_str": "1896271122",
                "indices": [
                    125,
                    140
                ]
            }
        ],
        "urls": [
            {
                "url": "http://t.co/KB5UANpDSr",
                "expanded_url": "http://bzfd.it/1xiSdyk",
                "display_url": "bzfd.it/1xiSdyk",
                "indices": [
                    68,
                    90
                ]
            }
        ],
        "media": [
            {
                "id": 530879486368034816,
                "id_str": "530879486368034816",
                "indices": [
                    91,
                    113
                ],
                "media_url": "http://pbs.twimg.com/media/B14QFIOCMAAyOD6.png",
                "media_url_https": "https://pbs.twimg.com/media/B14QFIOCMAAyOD6.png",
                "url": "http://t.co/N826YRUFMY",
                "display_url": "pic.twitter.com/N826YRUFMY",
                "expanded_url": "https://twitter.com/BuzzFeed/status/531085761521528834/photo/1",
                "type": "photo",
                "sizes": {
                    "small": {
                        "w": 500,
                        "h": 592,
                        "resize": "fit"
                    },
                    "large": {
                        "w": 500,
                        "h": 592,
                        "resize": "fit"
                    },
                    "medium": {
                        "w": 500,
                        "h": 592,
                        "resize": "fit"
                    },
                    "thumb": {
                        "w": 150,
                        "h": 150,
                        "resize": "crop"
                    }
                },
                "source_status_id": 531085761521528834,
                "source_status_id_str": "531085761521528834",
                "source_user_id": 5695632,
                "source_user_id_str": "5695632"
            }
        ]
    },
    "extended_entities": {
        "media": [
            {
                "id": 530879486368034816,
                "id_str": "530879486368034816",
                "indices": [
                    91,
                    113
                ],
                "media_url": "http://pbs.twimg.com/media/B14QFIOCMAAyOD6.png",
                "media_url_https": "https://pbs.twimg.com/media/B14QFIOCMAAyOD6.png",
                "url": "http://t.co/N826YRUFMY",
                "display_url": "pic.twitter.com/N826YRUFMY",
                "expanded_url": "https://twitter.com/BuzzFeed/status/531085761521528834/photo/1",
                "type": "photo",
                "sizes": {
                    "small": {
                        "w": 500,
                        "h": 592,
                        "resize": "fit"
                    },
                    "large": {
                        "w": 500,
                        "h": 592,
                        "resize": "fit"
                    },
                    "medium": {
                        "w": 500,
                        "h": 592,
                        "resize": "fit"
                    },
                    "thumb": {
                        "w": 150,
                        "h": 150,
                        "resize": "crop"
                    }
                },
                "source_status_id": 531085761521528834,
                "source_status_id_str": "531085761521528834",
                "source_user_id": 5695632,
                "source_user_id_str": "5695632"
            }
        ]
    },
    "source": "<a href=\"http://twitter.com/download/iphone\" rel=\"nofollow\">Twitter for iPhone</a>",
    "in_reply_to_status_id": 531085761521528834,
    "in_reply_to_status_id_str": "531085761521528834",
    "in_reply_to_user_id": 5695632,
    "in_reply_to_user_id_str": "5695632",
    "in_reply_to_screen_name": "BuzzFeed",
    "user": {
        "id": 2574222226,
        "id_str": "2574222226",
        "name": "blake.",
        "screen_name": "theblakerz",
        "location": "In the Doghouse",
        "description": "I like showing people videos they hate. I play Pokémon go. “If you make enough bad decisions, every once in a while things will work out for you.” -Geoff Ramsey",
        "url": "https://t.co/hXmtpTb4oo",
        "entities": {
            "url": {
                "urls": [
                    {
                        "url": "https://t.co/hXmtpTb4oo",
                        "expanded_url": "http://42069.au",
                        "display_url": "42069.au",
                        "indices": [
                            0,
                            23
                        ]
                    }
                ]
            },
            "description": {
                "urls": []
            }
        },
        "protected": false,
        "followers_count": 166,
        "friends_count": 164,
        "listed_count": 4,
        "created_at": "Sat May 31 18:23:29 +0000 2014",
        "favourites_count": 32014,
        "utc_offset": null,
        "time_zone": null,
        "geo_enabled": true,
        "verified": false,
        "statuses_count": 38820,
        "lang": null,
        "contributors_enabled": false,
        "is_translator": false,
        "is_translation_enabled": false,
        "profile_background_color": "C0DEED",
        "profile_background_image_url": "http://abs.twimg.com/images/themes/theme1/bg.png",
        "profile_background_image_url_https": "https://abs.twimg.com/images/themes/theme1/bg.png",
        "profile_background_tile": true,
        "profile_image_url": "http://pbs.twimg.com/profile_images/1424357510719356934/iP4CawQ6_normal.jpg",
        "profile_image_url_https": "https://pbs.twimg.com/profile_images/1424357510719356934/iP4CawQ6_normal.jpg",
        "profile_banner_url": "https://pbs.twimg.com/profile_banners/2574222226/1513937908",
        "profile_link_color": "981CEB",
        "profile_sidebar_border_color": "000000",
        "profile_sidebar_fill_color": "DDEEF6",
        "profile_text_color": "0084B4",
        "profile_use_background_image": true,
        "has_extended_profile": true,
        "default_profile": false,
        "default_profile_image": false,
        "following": false,
        "follow_request_sent": false,
        "notifications": false,
        "translator_type": "none",
        "withheld_in_countries": []
    },
    "geo": null,
    "coordinates": null,
    "place": null,
    "contributors": null,
    "is_quote_status": false,
    "retweet_count": 0,
    "favorite_count": 1,
    "favorited": false,
    "retweeted": false,
    "possibly_sensitive": true,
    "possibly_sensitive_appealable": false,
    "lang": "en"
}