{
    "contributors": null,
    "coordinates": null,
    "created_at": "Mon Jan 05 15:42:49 +0000 2015",
    "entities": {
        "hashtags": [],
        "symbols": [],
        "urls": [],
        "user_mentions": [
            {
                "id": 2363072078,
                "id_str": "2363072078",
                "indices": [
                    0,
                    15
                ],
                "name": "Ammaarah\ud83e\udddb\ud83c\udffc\u200d\u2640\ufe0f",
                "screen_name": "AmmaarahHafeez"
            }
        ]
    },
    "favorite_count": 1,
    "favorited": false,
    "geo": null,
    "id": 552128092282437632,
    "id_str": "552128092282437632",
    "in_reply_to_screen_name": "AmmaarahHafeez",
    "in_reply_to_status_id": 552127834790330370,
    "in_reply_to_status_id_str": "552127834790330370",
    "in_reply_to_user_id": 2363072078,
    "in_reply_to_user_id_str": "2363072078",
    "is_quote_status": false,
    "lang": "en",
    "place": null,
    "retweet_count": 0,
    "retweeted": false,
    "source": "<a href=\"http://twitter.com/download/iphone\" rel=\"nofollow\">Twitter for iPhone</a>",
    "text": "@AmmaarahHafeez the breach",
    "truncated": false,
    "user": {
        "contributors_enabled": false,
        "created_at": "Fri Jul 31 14:57:54 +0000 2009",
        "default_profile": false,
        "default_profile_image": false,
        "description": "#thePhaRaOhSreturn OUT NOW",
        "entities": {
            "description": {
                "urls": []
            },
            "url": {
                "urls": [
                    {
                        "display_url": "flyisfly.com",
                        "expanded_url": "http://flyisfly.com",
                        "indices": [
                            0,
                            23
                        ],
                        "url": "https://t.co/wcE6afSghG"
                    }
                ]
            }
        },
        "favourites_count": 17887,
        "follow_request_sent": false,
        "followers_count": 77155,
        "following": false,
        "friends_count": 2912,
        "geo_enabled": false,
        "has_extended_profile": false,
        "id": 61788692,
        "id_str": "61788692",
        "is_translation_enabled": false,
        "is_translator": false,
        "lang": null,
        "listed_count": 173,
        "location": "B E A S T   C O A S T ",
        "name": "#thePhaRaOhSreturn",
        "notifications": false,
        "profile_background_color": "C0DEED",
        "profile_background_image_url": "http://abs.twimg.com/images/themes/theme1/bg.png",
        "profile_background_image_url_https": "https://abs.twimg.com/images/themes/theme1/bg.png",
        "profile_background_tile": true,
        "profile_banner_url": "https://pbs.twimg.com/profile_banners/61788692/1644517202",
        "profile_image_url": "http://pbs.twimg.com/profile_images/1491143748545302528/LBhRio2i_normal.jpg",
        "profile_image_url_https": "https://pbs.twimg.com/profile_images/1491143748545302528/LBhRio2i_normal.jpg",
        "profile_link_color": "ABB8C2",
        "profile_sidebar_border_color": "FFFFFF",
        "profile_sidebar_fill_color": "DDEEF6",
        "profile_text_color": "333333",
        "profile_use_background_image": true,
        "protected": false,
        "screen_name": "CJFLY_",
        "statuses_count": 90562,
        "time_zone": null,
        "translator_type": "none",
        "url": "https://t.co/wcE6afSghG",
        "utc_offset": null,
        "verified": true,
        "withheld_in_countries": []
    }
}