{
    "contributors": null,
    "coordinates": null,
    "created_at": "Mon Jun 22 06:47:59 +0000 2015",
    "entities": {
        "hashtags": [],
        "symbols": [],
        "urls": [],
        "user_mentions": [
            {
                "id": 2739149852,
                "id_str": "2739149852",
                "indices": [
                    0,
                    15
                ],
                "name": "BobbyPlattz",
                "screen_name": "MasterMind5151"
            }
        ]
    },
    "favorite_count": 0,
    "favorited": false,
    "geo": null,
    "id": 612874655183929344,
    "id_str": "612874655183929344",
    "in_reply_to_screen_name": "MasterMind5151",
    "in_reply_to_status_id": 612872838215696384,
    "in_reply_to_status_id_str": "612872838215696384",
    "in_reply_to_user_id": 2739149852,
    "in_reply_to_user_id_str": "2739149852",
    "is_quote_status": false,
    "lang": "en",
    "place": null,
    "retweet_count": 2,
    "retweeted": false,
    "source": "<a href=\"http://twitter.com/download/iphone\" rel=\"nofollow\">Twitter for iPhone</a>",
    "text": "@MasterMind5151  What's sick, is the message these groups are pushing? What's sicker? Repubs sucking up to them, &amp; getting in bed w/ them",
    "truncated": false,
    "user": {
        "contributors_enabled": false,
        "created_at": "Wed Feb 09 18:36:08 +0000 2011",
        "default_profile": true,
        "default_profile_image": false,
        "description": "My two passions in life, hence the title. Dedicated to calling out repubs BS every chance I get.",
        "entities": {
            "description": {
                "urls": []
            }
        },
        "favourites_count": 43892,
        "follow_request_sent": false,
        "followers_count": 1547,
        "following": false,
        "friends_count": 0,
        "geo_enabled": true,
        "has_extended_profile": false,
        "id": 249761195,
        "id_str": "249761195",
        "is_translation_enabled": false,
        "is_translator": false,
        "lang": null,
        "listed_count": 61,
        "location": "",
        "name": "Pot&Politics",
        "notifications": false,
        "profile_background_color": "C0DEED",
        "profile_background_image_url": "http://abs.twimg.com/images/themes/theme1/bg.png",
        "profile_background_image_url_https": "https://abs.twimg.com/images/themes/theme1/bg.png",
        "profile_background_tile": false,
        "profile_image_url": "http://pbs.twimg.com/profile_images/911789991646416896/q9VYsSQr_normal.jpg",
        "profile_image_url_https": "https://pbs.twimg.com/profile_images/911789991646416896/q9VYsSQr_normal.jpg",
        "profile_link_color": "1DA1F2",
        "profile_sidebar_border_color": "C0DEED",
        "profile_sidebar_fill_color": "DDEEF6",
        "profile_text_color": "333333",
        "profile_use_background_image": true,
        "protected": false,
        "screen_name": "PotPolitics",
        "statuses_count": 123462,
        "time_zone": null,
        "translator_type": "none",
        "url": null,
        "utc_offset": null,
        "verified": false,
        "withheld_in_countries": []
    }
}